armenian_transliterate.py
armenian_latin_to_armenian_hy-0.0.3.dist-info/METADATA
armenian_latin_to_armenian_hy-0.0.3.dist-info/WHEEL
armenian_latin_to_armenian_hy-0.0.3.dist-info/top_level.txt
armenian_latin_to_armenian_hy-0.0.3.dist-info/RECORD
