Metadata-Version: 2.1
Name: armenian_latin_to_armenian_hy
Version: 0.0.3
Summary: Transliteration from Latin Armenian language to Armenian
Classifier: Programming Language :: Python :: 3
Classifier: License :: OSI Approved :: MIT License
Classifier: Operating System :: OS Independent
Requires-Python: >=3.6
